tablediff/__init__.py
tablediff/cli.py
tablediff/engine.py
tablediff/models.py
tablediff/renderers.py
tablediff_cli-0.3.0.dist-info/licenses/LICENSE
tablediff_cli-0.3.0.dist-info/METADATA
tablediff_cli-0.3.0.dist-info/WHEEL
tablediff_cli-0.3.0.dist-info/entry_points.txt
tablediff_cli-0.3.0.dist-info/top_level.txt
tablediff_cli-0.3.0.dist-info/RECORD
