Metadata-Version: 2.4
Name: tablediff-cli
Version: 0.3.0
Summary: CLI tool for data diffing between two tables
Author-email: Oleg Agapov <oleg.agapov.ua@gmail.com>
License: Apache-2.0
Project-URL: Homepage, https://github.com/oleg-agapov/tablediff
Keywords: data diff,table diff,sql diff,data diffing
Classifier: Development Status :: 4 - Beta
Classifier: Operating System :: OS Independent
Classifier: Intended Audience :: Developers
Classifier: Topic :: Database
Classifier: Programming Language :: Python :: 3.10
Classifier: Programming Language :: Python :: 3.11
Classifier: Programming Language :: Python :: 3.12
Classifier: Programming Language :: Python :: 3.13
Requires-Python: >=3.10
License-File: LICENSE
Requires-Dist: rich
Requires-Dist: reladiff
Provides-Extra: duckdb
Requires-Dist: reladiff[duckdb]; extra == "duckdb"
Provides-Extra: mysql
Requires-Dist: reladiff[mysql]; extra == "mysql"
Provides-Extra: postgresql
Requires-Dist: reladiff[postgresql]; extra == "postgresql"
Provides-Extra: snowflake
Requires-Dist: reladiff[snowflake]; extra == "snowflake"
Requires-Dist: snowflake-connector-python[secure-local-storage]; extra == "snowflake"
Provides-Extra: clickhouse
Requires-Dist: reladiff[clickhouse]; extra == "clickhouse"
Provides-Extra: presto
Requires-Dist: reladiff[presto]; extra == "presto"
Provides-Extra: bigquery
Requires-Dist: google-cloud-bigquery; extra == "bigquery"
Provides-Extra: oracle
Requires-Dist: reladiff[oracle]; extra == "oracle"
Provides-Extra: trino
Requires-Dist: reladiff[trino]; extra == "trino"
Provides-Extra: vertica
Requires-Dist: reladiff[vertica]; extra == "vertica"
Provides-Extra: all
Requires-Dist: reladiff[all]; extra == "all"
Requires-Dist: snowflake-connector-python[secure-local-storage]; extra == "all"
Provides-Extra: dev
Requires-Dist: pytest; extra == "dev"
Requires-Dist: duckdb; extra == "dev"
Dynamic: license-file
